{
    "packages": {
        "generoi/wp-all-export-pro": [
            {
                "name": "generoi/wp-all-export-pro",
                "version": "1.9.1",
                "version_normalized": "1.9.1.0",
                "source": {
                    "type": "git",
                    "url": "git@github.com:generoi/wp-all-export-pro.git",
                    "reference": "7f456b67422c54ea508b49d29d0194efe1d9de47"
                },
                "dist": {
                    "type": "zip",
                    "url": "https://api.github.com/repos/generoi/wp-all-export-pro/zipball/7f456b67422c54ea508b49d29d0194efe1d9de47",
                    "reference": "7f456b67422c54ea508b49d29d0194efe1d9de47",
                    "shasum": ""
                },
                "time": "2024-10-21T15:53:43+00:00",
                "type": "wordpress-plugin",
                "homepage": "http://www.wpallimport.com",
                "support": {
                    "source": "https://github.com/generoi/wp-all-export-pro/tree/1.9.1",
                    "issues": "https://github.com/generoi/wp-all-export-pro/issues"
                }
            },
            {
                "name": "generoi/wp-all-export-pro",
                "version": "1.9.2",
                "version_normalized": "1.9.2.0",
                "source": {
                    "type": "git",
                    "url": "git@github.com:generoi/wp-all-export-pro.git",
                    "reference": "21e255bf69cd9a10875a9b54ed6002a39c6b0da7"
                },
                "dist": {
                    "type": "zip",
                    "url": "https://api.github.com/repos/generoi/wp-all-export-pro/zipball/21e255bf69cd9a10875a9b54ed6002a39c6b0da7",
                    "reference": "21e255bf69cd9a10875a9b54ed6002a39c6b0da7",
                    "shasum": ""
                },
                "time": "2025-01-02T04:09:29+00:00",
                "type": "wordpress-plugin",
                "homepage": "http://www.wpallimport.com",
                "support": {
                    "source": "https://github.com/generoi/wp-all-export-pro/tree/1.9.2",
                    "issues": "https://github.com/generoi/wp-all-export-pro/issues"
                }
            },
            {
                "name": "generoi/wp-all-export-pro",
                "version": "1.9.3",
                "version_normalized": "1.9.3.0",
                "source": {
                    "type": "git",
                    "url": "git@github.com:generoi/wp-all-export-pro.git",
                    "reference": "7e4770ac3be4d8befcaebda8fb16bd8db9bd12ed"
                },
                "dist": {
                    "type": "zip",
                    "url": "https://api.github.com/repos/generoi/wp-all-export-pro/zipball/7e4770ac3be4d8befcaebda8fb16bd8db9bd12ed",
                    "reference": "7e4770ac3be4d8befcaebda8fb16bd8db9bd12ed",
                    "shasum": ""
                },
                "time": "2025-01-08T04:09:37+00:00",
                "type": "wordpress-plugin",
                "homepage": "http://www.wpallimport.com",
                "support": {
                    "source": "https://github.com/generoi/wp-all-export-pro/tree/1.9.3",
                    "issues": "https://github.com/generoi/wp-all-export-pro/issues"
                }
            },
            {
                "name": "generoi/wp-all-export-pro",
                "version": "1.9.4",
                "version_normalized": "1.9.4.0",
                "source": {
                    "type": "git",
                    "url": "git@github.com:generoi/wp-all-export-pro.git",
                    "reference": "c24438b6b535943bd339bc669ed9cace79d9195b"
                },
                "dist": {
                    "type": "zip",
                    "url": "https://api.github.com/repos/generoi/wp-all-export-pro/zipball/c24438b6b535943bd339bc669ed9cace79d9195b",
                    "reference": "c24438b6b535943bd339bc669ed9cace79d9195b",
                    "shasum": ""
                },
                "time": "2025-01-28T04:09:07+00:00",
                "type": "wordpress-plugin",
                "homepage": "http://www.wpallimport.com",
                "support": {
                    "source": "https://github.com/generoi/wp-all-export-pro/tree/1.9.4",
                    "issues": "https://github.com/generoi/wp-all-export-pro/issues"
                }
            },
            {
                "name": "generoi/wp-all-export-pro",
                "version": "1.9.6",
                "version_normalized": "1.9.6.0",
                "source": {
                    "type": "git",
                    "url": "git@github.com:generoi/wp-all-export-pro.git",
                    "reference": "4c79447c9c464e4bc89ff0019fca6d965c482296"
                },
                "dist": {
                    "type": "zip",
                    "url": "https://api.github.com/repos/generoi/wp-all-export-pro/zipball/4c79447c9c464e4bc89ff0019fca6d965c482296",
                    "reference": "4c79447c9c464e4bc89ff0019fca6d965c482296",
                    "shasum": ""
                },
                "time": "2025-03-01T04:08:52+00:00",
                "type": "wordpress-plugin",
                "homepage": "http://www.wpallimport.com",
                "support": {
                    "source": "https://github.com/generoi/wp-all-export-pro/tree/1.9.6",
                    "issues": "https://github.com/generoi/wp-all-export-pro/issues"
                }
            }
        ]
    }
}
